Workbook

Sheet Input
A1: Inserire Nome Azienda | C1: Tipologia | D1: Grade | E1: Fido
A2: Inserire ultimo anno disponibile di bilancio | C2: Fornitore
A4: CONTO ECONOMICO
A6: Voce | B6: =$B$2 | C6: =$B$6-1 | D6: =$B$6-2
A7: Valore della Produzione | B7: 0 | C7: 0
A8: Ricavi di vendita | B8: 0 | C8: 0
A9: Costi della Produzione | B9: 0 | C9: 0
A10: Costi per Materie | B10: 0 | C10: 0
A11: Costi per Servizi | B11: 0 | C11: 0
A12: Costi per godimento beni di terzi | B12: 0 | C12: 0
A13: Costi Personale | B13: 0 | C13: 0
A14: Ammortamenti | B14: 0 | C14: 0
A15: Accantonamenti per rischi | B15: 0 | C15: 0
A16: Oneri diversi di gestione | B16: 0 | C16: 0
A17: EBIT | B17: 0 | C17: 0
A18: Proventi Finanziari | B18: 0 | C18: 0
... A21: Dipendenti | B21: 0 | C21: 0
A24: STATO PATRIMONIALE
A26: Voce | B26: =$B$6 | C26: =$C$6 | D26: =$D$6
A27: Immobilizzazioni | B27: 0 | C27: 0
A28: Rimanenze | B28: 0 | C28: 0
A29: Crediti | B29: 0 | C29: 0
A30: Attività Finanziarie | B30: 0 | C30: 0
A31: Disponibilità Liquide | B31: 0 | C31: 0
A32: Ratei e Risconti Attivi | B32: 0 | C32: 0
A33: Totale Attivo | B33: 0 | C33: 0
A34: Totale Patrimonio Netto | B34: 0 | C34: 0
A35: Fondi per rischi e oneri | B35: 0 | C35: 0
A36: Trattamento di fine rapporto di lavoro subordinato | B36: 0 | C36: 0
A37: Totale Debiti | B37: 0 | C37: 0 | E37: =E38+E39 | F37: =F38+F39 | G37: =G38+G39
A38: Debiti esigibili a breve | B38: 0 | C38: 0 | E38: =B38-B41 | F38: =C38-C41 | G38: =D38-D41
A39: Debiti esigibili oltre l’esercizio successivo | B39: 0 | C39: 0 | E39: =B39-B42 | F39: =C39-C42 | G39: =D39-D42
A40: Totale Debiti Finanziari | B40: 0 | C40: 0
A41: Debiti Finanziari esigibili a breve | B41: 0 | C41: 0
A42: Debiti Finanziari esigibili oltre l’esercizio successivo | B42: 0 | C42: 0
A43: Ratei e Risconti Passivi | B43: 0 | C43: 0
A44: Debiti verso fornitori | B44: 0 | C44: 0
A45: Crediti verso clienti | B45: 0 | C45: 0
A46: ATECO 2007
A47: Partita IVA | E47: =IF(LEN(B47)=10,"0"&B47,IF(LEN(B47)=9,"00"&B47,B47))
A48: Forma Giuridica
A49: Sede
A52: Verifica Attivo | B52: =SUM(B27:B32)=B33 | C52: =SUM(C27:C32)=C33 | D52: =SUM(D27:D32)=D33
A53: Verifica Passivo | B53: =(B40+E37+B36+B35+B34+B43)=B33 | C53: =(C43+C40+F37+C36+C35+C34)=C33 | D53: =(D43+D40+G37+D36+D35+D34)=D33
H55: Grade
A56: Liquidità | B56: Valore di bilancio | C56: Grade | D56: Peso | E56: Grade Ponderato | F56: Peso % | H56: 1 | I56: 2 | J56: 3 | K56: 4 | L56: 5 | M56: 6 | N56: 7 | O56: 8 | P56: 9 | Q56: 10
A57: Test Acido | B57: =+Report!B126 | C57: =IF(B57>H57,$H$56,IF(B57>I57,$I$56,IF(B57>J57,$J$56,IF(B57>K57,$K$56,IF(B57>L57,$L$56,IF(B57>M57,$M$56,IF(B57>N57,$N$56,IF(B57>O57,$O$56,IF(B57>P57,$P$56,$Q$56))))))))) | D57: 0.1 | E57: =C57*D57 | F57: =E57/$E$75 | H57: 1.5 | I57: 1.3 | J57: 1.1 | K57: 0.9 | L57: 0.8 | M57: 0.7 | N57: 0.6 | O57: 0.5 | P57: 0.4 | Q57: <
A58: Current Ratio | B58: =+Report!B127 | C58: =IF(B58>H58,$H$56,IF(B58>I58,$I$56,IF(B58>J58,$J$56,IF(B58>K58,$K$56,IF(B58>L58,$L$56,IF(B58>M58,$M$56,IF(B58>N58,$N$56,IF(B58>O58,$O$56,IF(B58>P58,$P$56,$Q$56))))))))) | D58: 0.1 | E58: =C58*D58 | F58: =E58/$E$75 | H58: 2 | I58: 1.8 | J58: 1.6 | K58: 1.4 | L58: 1.2 | M58: 1 | N58: 0.9 | O58: 0.8 | P58: 0.7 | Q58: <
A59: Indebitamento e sostenibilità del debito
A60: Rapporto Indebitamento | B60: =+Report!B129 | C60: =IF(B60<H60,$H$56,IF(B60<I60,$I$56,IF(B60<J60,$J$56,IF(B60<K60,$K$56,IF(B60<L60,$L$56,IF(B60<M60,$M$56,IF(B60<N60,$N$56,IF(B60<O60,$O$56,IF(B60<P60,$P$56,$Q$56))))))))) | D60: 0.1 | E60: =C60*D60 | F60: =E60/$E$75 | H60: 0.2 | I60: 0.4 | J60: 0.6 | K60: 0.8 | L60: 1 | M60: 1.2 | N60: 1.5 | O60: 1.8 | P60: 2 | Q60: >
A61: PFN/EBITDA | B61: =+Report!B131 | C61: =IF(AND(B61="Non Calcolabile",B19=0),"0",IF(AND(B61="Non Calcolabile",B19<>0),L56,IF(AND(B61>0,Report!B130>0,Report!B136>0),Input!J56,IF(AND(B61>0,Report!B130<0,Report!B136<0),Input!O56,IF(B61>H61,$H$56,IF(B61>I61,$I$56,IF(B61>J61,$J$56,IF(B61>K61,$K$56,IF(B61>L61,$L$56,IF(B61>M61,$M$56,IF(B61>N61,$N$56,IF(B61>O61,$O$56,IF(B61>P61,$P$56,$Q$56))))))))))))) | D61: 0.15 | E61: =C61*D61 | F61: =E61/$E$75 | H61: 2 | I61: 1.5 | J61: 1 | K61: 0.5 | L61: 0 | M61: -0.5 | N61: -1 | O61: -1.5 | P61: -2 | Q61: >
A62: IMS | B62: =+Report!B76/Report!B61 | C62: =IF(B62>H62,$H$56,IF(B62>I62,$I$56,IF(B62>J62,$J$56,IF(B62>K62,$K$56,IF(B62>L62,$L$56,IF(B62>M62,$M$56,IF(B62>N62,$N$56,IF(B62>O62,$O$56,IF(B62>P62,$P$56,$Q$56))))))))) | D62: 0.05 | E62: =C62*D62 | F62: =E62/$E$75 | H62: 1.5 | I62: 1.3 | J62: 1.1 | K62: 1 | L62: 0.9 | M62: 0.8 | N62: 0.7 | O62: 0.6 | P62: 0.5 | Q62: <
A63: Interest Coverage Ratio | B63: =+Report!B136/Report!B118 | C63: =IF(B63=0,H56,IF(B63>H63,$H$56,IF(B63>I63,$I$56,IF(B63>J63,$J$56,IF(B63>K63,$K$56,IF(B63>L63,$L$56,IF(B63>M63,$M$56,IF(B63>N63,$N$56,IF(B63>O63,$O$56,IF(B63>P63,$P$56,$Q$56)))))))))) | D63: 0.1 | E63: =C63*D63 | F63: =E63/$E$75 | H63: 10 | I63: 8 | J63: 6 | K63: 4 | L63: 2.5 | M63: 1.5 | N63: 1.2 | O63: 1 | P63: 0.8 | Q63: <
A64: Redditività
A65: ROS | B65: =+Report!B133 | C65: =IF(B65>H65,$H$56,IF(B65>I65,$I$56,IF(B65>J65,$J$56,IF(B65>K65,$K$56,IF(B65>L65,$L$56,IF(B65>M65,$M$56,IF(B65>N65,$N$56,IF(B65>O65,$O$56,IF(B65>P65,$P$56,$Q$56))))))))) | D65: 0.1 | E65: =C65*D65 | F65: =E65/$E$75 | H65: 0.2 | I65: 0.13 | J65: 0.11 | K65: 0.09 | L65: 0.07 | M65: 0.05 | N65: 0.03 | O65: 0.01 | P65: 0 | Q65: <
A66: ROE | B66: =+Report!B134 | C66: =IF(B66>H66,$H$56,IF(B66>I66,$I$56,IF(B66>J66,$J$56,IF(B66>K66,$K$56,IF(B66>L66,$L$56,IF(B66>M66,$M$56,IF(B66>N66,$N$56,IF(B66>O66,$O$56,IF(B66>P66,$P$56,$Q$56))))))))) | D66: 0.05 | E66: =C66*D66 | F66: =E66/$E$75 | H66: 0.25 | I66: 0.2 | J66: 0.15 | K66: 0.12 | L66: 0.1 | M66: 0.08 | N66: 0.06 | O66: 0.04 | P66: 0.02 | Q66: <
A67: ROI | B67: =+Report!B135 | C67: =IF(B67>H67,$H$56,IF(B67>I67,$I$56,IF(B67>J67,$J$56,IF(B67>K67,$K$56,IF(B67>L67,$L$56,IF(B67>M67,$M$56,IF(B67>N67,$N$56,IF(B67>O67,$O$56,IF(B67>P67,$P$56,$Q$56))))))))) | D67: 0.05 | E67: =C67*D67 | F67: =E67/$E$75 | H67: 0.25 | I67: 0.2 | J67: 0.15 | K67: 0.12 | L67: 0.1 | M67: 0.08 | N67: 0.06 | O67: 0.04 | P67: 0.02 | Q67: <
A68: EBITDA% | B68: =+Report!B136/Report!B98 | C68: =IF(B68>H68,$H$56,IF(B68>I68,$I$56,IF(B68>J68,$J$56,IF(B68>K68,$K$56,IF(B68>L68,$L$56,IF(B68>M68,$M$56,IF(B68>N68,$N$56,IF(B68>O68,$O$56,IF(B68>P68,$P$56,$Q$56))))))))) | D68: 0.1 | E68: =C68*D68 | F68: =E68/$E$75 | H68: 0.15 | I68: 0.13 | J68: 0.1 | K68: 0.08 | L68: 0.06 | M68: 0.04 | N68: 0.02 | O68: 0.01 | P68: 0 | Q68: <
A69: EBIT% | B69: =+Report!B116 | C69: =IF(B69>H69,$H$56,IF(B69>I69,$I$56,IF(B69>J69,$J$56,IF(B69>K69,$K$56,IF(B69>L69,$L$56,IF(B69>M69,$M$56,IF(B69>N69,$N$56,IF(B69>O69,$O$56,IF(B69>P69,$P$56,$Q$56))))))))) | D69: 0.05 | E69: =C69*D69 | F69: =E69/$E$75 | H69: 0.13 | I69: 0.11 | J69: 0.1 | K69: 0.08 | L69: 0.06 | M69: 0.04 | N69: 0.02 | O69: 0 | P69: -0.02 | Q69: <
A70: Risultato d'esercizio% | B70: =+Report!B119/Report!B98 | C70: =IF(B70>H70,$H$56,IF(B70>I70,$I$56,IF(B70>J70,$J$56,IF(B70>K70,$K$56,IF(B70>L70,$L$56,IF(B70>M70,$M$56,IF(B70>N70,$N$56,IF(B70>O70,$O$56,IF(B70>P70,$P$56,$Q$56))))))))) | D70: 0.025 | E70: =C70*D70 | F70: =E70/$E$75 | H70: 0.1 | I70: 0.08 | J70: 0.06 | K70: 0.04 | L70: 0.02 | M70: 0.01 | N70: 0 | O70: -0.03 | P70: -0.05 | Q70: <
A71: Efficienza
A72: Asset Turnover (AT) | B72: =+Report!B138 | C72: =IF(B72>H72,$H$56,IF(B72>I72,$I$56,IF(B72>J72,$J$56,IF(B72>K72,$K$56,IF(B72>L72,$L$56,IF(B72>M72,$M$56,IF(B72>N72,$N$56,IF(B72>O72,$O$56,IF(B72>P72,$P$56,$Q$56))))))))) | D72: 0.025 | E72: =C72*D72 | F72: =E72/$E$75 | H72: 2 | I72: 1.8 | J72: 1.6 | K72: 1.4 | L72: 1.2 | M72: 1 | N72: 0.9 | O72: 0.8 | P72: 0.7 | Q72: <
E74: Grade
E75: =AVERAGE(C57:C72)
C82: Grade | D82: Fido Massimo
C83: =IF(I92="Microimpresa",ROUND(E75,0)+2,IF(I92="Piccola impresa",ROUND(E75,0)+1,IF(I92="Media impresa",ROUND(E75+0.5,0),IF(I92="Grande impresa",ROUND(E75,0))))) | D83: =INDEX($H$95:$H$104,MATCH(C83,$G$95:$G$104,0))*INDEX($K$84:$K$87,MATCH(I92,$G$84:$G$87,0)) | G83: Categoria | H83: Totale dello Stato Patrimoniale (€) | I83: Ricavi Netti delle Vendite e delle Prestazioni (€) | J83: Numero Medio dei Dipendenti | K83: Ponderazione Dimensione Impresa
F84: 1 | G84: Microimpresa | H84: 450000 | I84: 900000 | J84: 10 | K84: 0.1
D85: ="0 € - "&TEXT(D83,"#.##0")&" €" | F85: 2 | G85: Piccola impresa | H85: 5000000 | I85: 10000000 | J85: 50 | K85: 0.2
F86: 3 | G86: Media impresa | H86: 25000000 | I86: 50000000 | J86: 250 | K86: 0.3
F87: 4 | G87: Grande impresa | H87: 25000000 | I87: 50000000 | J87: 250 | K87: 0.5
H88: =+B33 | I88: =B8 | J88: =$B$21
H89: =IF(H88<=H84,$G$84,IF(AND(H88<=H85,H88>H84),$G$85,IF(AND(H88<=H86,H88>H85),$G$86,IF(H88>H86,$G$87)))) | I89: =IF(I88<=I84,$G$84,IF(AND(I88<=I85,I88>I84),$G$85,IF(AND(I88<=I86,I88>I85),$G$86,IF(I88>I86,$G$87)))) | J89: =IF(J88<=J84,$G$84,IF(AND(J88<=J85,J88>J84),$G$85,IF(AND(J88<=J86,J88>J85),$G$86,IF(J88>J86,$G$87))))
H90: =INDEX($F$84:$F$87,MATCH(H89,$G$84:$G$87,0)) | I90: =INDEX($F$84:$F$87,MATCH(I89,$G$84:$G$87,0)) | J90: =INDEX($F$84:$F$87,MATCH(J89,$G$84:$G$87,0))
I91: =_xlfn.MODE.SNGL(H90:J90)
I92: =IFERROR(INDEX(G84:G87,MATCH(I91,$F$84:$F$87,0)),INDEX($G$84:$G$87,MATCH(MEDIAN(H90:J90),$F$84:$F$87,0)))
G94: Grade | H94: Max
G95: 1 | H95: 1000000
G96: 2 | H96: 1000000
G97: 3 | H97: 1000000
G98: 4 | H98: 800000
G99: 5 | H99: 350000
G100: 6 | H100: 200000
G101: 7 | H101: 50000
G102: 8 | H102: 0
G103: 9 | H103: 0
G104: 10 | H104: 0
B109: =$C$83
A110: Grafico | B110: Nero | C110: Rosso | D110: Giallo | E110: Verde
B111: =$C$83 | C111: =$C$83 | D111: =$C$83 | E111: =$C$83
B112: =10-B113 | C112: =10-C113 | D112: =10-D113 | E112: =10-E113
B113: =IF(B111=10,B111,"") | C113: =IF(AND(C111>=7,C111<=9),C111,"") | D113: =IF(AND(D111>=4,D111<=6),D111,"") | E113: =IF(AND(E111>=1,E111<=3),E111,"")
B114: 10 | C114: 10 | D114: 10 | E114: 10
B118: Valore | C118: Rating | D118: Molto Critica | E118: Critica | F118: Adeguata | G118: Positiva | H118: Eccellente
D119: 5 | E119: 4 | F119: 3 | G119: 2 | H119: 1
A120: Reddituale
A121: Crescita Fatturato | B121: =+Report!D98 | C121: =IF(B121<=D121,$D$119,IF(B121<=E121,$E$119,IF(B121<=F121,$F$119,IF(B121<=G121,$G$119,IF(OR(B121<=H121,B121>=H121),$H$119,""))))) | D121: -0.1 | E121: -0.05 | F121: 0 | G121: 0.05 | H121: 0.1
A122: Crescita EBIT | B122: =+Report!D115 | C122: =IF(B122<=D122,$D$119,IF(B122<=E122,$E$119,IF(B122<=F122,$F$119,IF(B122<=G122,$G$119,IF(OR(B122<=H122,B122>=H122),$H$119,""))))) | D122: -0.07 | E122: -0.03 | F122: 0 | G122: 0.03 | H122: 0.07
A123: Crescita Peso EBIT | B123: =+Report!B116-Report!C116 | C123: =IF(B123<=D123,$D$119,IF(B123<=E123,$E$119,IF(B123<=F123,$F$119,IF(B123<=G123,$G$119,IF(OR(B123<=H123,B123>=H123),$H$119,""))))) | D123: -0.05 | E123: -0.03 | F123: 0 | G123: 0.03 | H123: 0.07
A124: Crescita Utile | B124: =+Report!D119 | C124: =IF(B124<=D124,$D$119,IF(B124<=E124,$E$119,IF(B124<=F124,$F$119,IF(B124<=G124,$G$119,IF(OR(B124<=H124,B124>=H124),$H$119,""))))) | D124: -0.03 | E124: -0.01 | F124: 0 | G124: 0.03 | H124: 0.05
A125: Crescita Peso Utile | B125: =+(Report!B119/Report!B98)-(Report!C119/Report!C98) | C125: =IF(B125<=D125,$D$119,IF(B125<=E125,$E$119,IF(B125<=F125,$F$119,IF(B125<=G125,$G$119,IF(OR(B125<=H125,B125>=H125),$H$119,""))))) | D125: -0.03 | E125: -0.01 | F125: 0 | G125: 0.02 | H125: 0.05
...

Sheet Report
B1: =Input!B1
A3: Profilo Società
A4: PARTITA IVA | B4: =Input!$E$47
A5: ATECO 2007 | B5: =Input!$B$46 | D5: Fido
A6: FORMA GIURIDICA | B6: =Input!$B$48 | D6: =IF(Input!E2="",Input!$D$85,Input!$E$2)
A7: SEDE | B7: =Input!$B$49
A10: Situazione Reddituale
A11: =IF(B11="Eccellente","nnnnnnnnnnnnn",IF(B11="Positiva","nnnnnnnnnn",IF(B11="Adeguata","nnnnnnn",IF(B11="Critica","nnnn",IF(B11="Molto Critica","n",""))))) | B11: Adeguata | D11: Grade
A13: Situazione Finanziaria
A14: =IF(B14="Eccellente","nnnnnnnnnnnnn",IF(B14="Positiva","nnnnnnnnnn",IF(B14="Adeguata","nnnnnnn",IF(B14="Critica","nnnn",IF(B14="Molto Critica","n",""))))) | B14: =INDEX(Input.$D$118:$H$118,MATCH(Input!C135,Input.$D$119:$H$119,0))
D15: =IF(Input!D2="",Input!$C$83,Input!$D$2)
A16: Situazione Patrimoniale
A17: =IF(B17="Eccellente","nnnnnnnnnnnnn",IF(B17="Positiva","nnnnnnnnnn",IF(B17="Adeguata","nnnnnnn",IF(B17="Critica","nnnn",IF(B17="Molto Critica","n",""))))) | B17: Adeguata
A20: Sintesi KPI | B20: =IF(B98>=1000000,TEXT(TRUNC(B98/1000000,2),"0,00")&" mln",IF(B98>=1000,TEXT(TRUNC(B98/1000,2),"0,00")&"k",TEXT(B98,"0,00")))
A22: Ricavi | B22: EBIT | C22: EBITDA | D22: Utile d'es.
A23: =+Input!B8 | B23: =+Input!B17 | C23: =+Input!B17+Input!B14 | D23: =+Input!B20
A24: =IFERROR(TEXT((Input!B8-Input!C8)/Input!C8,"+0,00%;-0,00%;0,00%") & " vs " & TEXT(Input!C8,"#.##0"),"n.d.") | B24: =IFERROR(TEXT((Input!B17-Input!C17)/Input!C17,"+0,00%;-0,00%;0,00%") & " vs " & TEXT(Input!C17,"#.##0"),"n.d.") | C24: =IFERROR(TEXT(((Input!B17+Input!B14)-(Input!C17+Input!C14))/(Input!C17+Input!C14),"+0,00%;-0,00%;0,00%") & " vs " & TEXT((Input!C17+Input!C14),"#.##0"),"n.d.") | D24: =IFERROR(TEXT((Input!B20-Input!C20)/Input!C20,"+0,00%;-0,00%;0,00%") & " vs " & TEXT(Input!C20,"#.##0"),"n.d.")
A26: Patr. Netto | B26: Deb. Fin. | C26: Disp. Liq. | D26: Dipendenti
A27: =+Input!B34 | B27: =+Input!B40 | C27: =+Input!B31 | D27: =+Input!B21
A28: =IFERROR(TEXT((Input!B34-Input!C34)/Input!C34,"+0,00%;-0,00%;0,00%") & " vs " & TEXT(Input!C34,"#.##0"),"n.d.") | B28: =IFERROR(TEXT((Input!B40-Input!C40)/Input!C40,"+0,00%;-0,00%;0,00%")&" vs "&TEXT(Input!C40,"#.##0"),"n.d.") | C28: =IFERROR(TEXT((Input!B31-Input!C31)/Input!C31,"+0,00%;-0,00%;0,00%") & " vs " & TEXT(Input!C31,"#.##0"),"n.d.") | D28: =IFERROR(TEXT((Input!B21-Input!C21)/Input!C21,"+0,00%;-0,00%;0,00%") & " vs " & TEXT(Input!C21,"#.##0"),"n.d.")
A31: Valutazione
A33: Ambito Economico | C33: Ambito Finanziario e Patrimoniale
A45: Sintesi | C45: Grade e Fido
A58: STATO PATRIMONIALE
A59: Voce | B59: =Input!$B$6 | C59: =Input!$C$6 | D59: Var %
A60: Attivo
A61: Immobilizzazioni | B61: =Input!B27 | C61: =Input!C27 | D61: =IFERROR((B61-C61)/C61,"")
A62: % Immob. su attivo | B62: =B$61/B$73 | C62: =C$61/C$73
A63: Rimanenze | B63: =Input!B28 | C63: =Input!C28 | D63: =IFERROR((B63-C63)/C63,"")
A64: % Rimanenze su attivo | B64: =B$63/B$73 | C64: =C$63/C$73
A65: Crediti | B65: =Input!B29 | C65: =Input!C29 | D65: =IFERROR((B65-C65)/C65,"")
A66: % Crediti su attivo | B66: =B$65/B$73 | C66: =C$65/C$73
A67: Attività Finanziarie | B67: =Input!B30 | C67: =Input!C30 | D67: =IFERROR((B67-C67)/C67,"")
A68: % Attivittà Finanziarie su attivo | B68: =B$67/B$73 | C68: =C$67/C$73
A69: Disponibilità Liquide | B69: =Input!B31 | C69: =Input!C31 | D69: =IFERROR((B69-C69)/C69,"")
A70: % Disp. Liq. su attivo | B70: =B$69/B$73 | C70: =C$69/C$73
A71: Ratei e Risconti Attivi | B71: =Input!B32 | C71: =Input!C32 | D71: =IFERROR((B71-C71)/C71,"")
A72: % Ratei e Risconti attivi su attivo | B72: =B$71/B$73 | C72: =C$71/C$73
A73: Totale Attivo | B73: =Input!B33 | C73: =Input!C33 | D73: =IFERROR((B73-C73)/C73,"")
A75: Passivo
A76: Patrimonio Netto | B76: =Input!B34 | C76: =Input!C34 | D76: =IFERROR((B76-C76)/C76,"")
A77: % Tot. Patr. Netto su Tot. Passivo | B77: =B$76/B$73 | C77: =C$76/C$73
A78: Fondi per rischi e oneri | B78: =Input!B35 | C78: =Input!C35 | D78: =IFERROR((B78-C78)/C78,"")
A79: % Fondi per rischi e oneri su Tot. Passivo | B79: =B$78/B$73 | C79: =C$78/C$73
A80: TFR | B80: =Input!B36 | C80: =Input!C36 | D80: =IFERROR((B80-C80)/C80,"")
A81: % TFR su Tot. Passivo | B81: =B$80/B$73 | C81: =C$80/C$73
A82: Debiti | B82: =Input!E37 | C82: =Input!F37 | D82: =IFERROR((B82-C82)/C82,"")
A83: -Debiti a BT | B83: =Input!E38 | C83: =Input!F38 | D83: =IFERROR((B83-C83)/C83,"")
A84: -Debiti a LT | B84: =Input!E39 | C84: =Input!F39 | D84: =IFERROR((B84-C84)/C84,"")
A85: % Tot. Debiti su Tot. Passivo | B85: =B$82/B$73 | C85: =C$82/C$73
A86: Debiti Finanziari | B86: =Input!B40 | C86: =Input!C40 | D86: =IFERROR((B86-C86)/C86,"")
A87: -Debiti Finanziari a BT | B87: =Input!B41 | C87: =Input!C41 | D87: =IFERROR((B87-C87)/C87,"")
A88: -Debiti Finanziari a LT | B88: =Input!B42 | C88: =Input!C42 | D88: =IFERROR((B88-C88)/C88,"")
A89: % Debiti Finanz. su Tot. Passivo | B89: =B$86/B$73 | C89: =C$86/C$73
A90: Ratei e Risconti Passivi | B90: =Input!B43 | C90: =Input!C43 | D90: =IFERROR((B90-C90)/C90,"")
A91: % Ratei e Risconti Passivi su Tot. Passivo | B91: =B$90/B$73 | C91: =C$90/C$73
A95: CONTO ECONOMICO
A96: Voce | B96: =Input!$B$6 | C96: =Input!$C$6 | D96: Var %
A98: Valore della Produzione | B98: =Input!B7 | C98: =Input!C7 | D98: =IFERROR((B98-C98)/C98,"")
A99: -Ricavi di vendita | B99: =Input!B8 | C99: =Input!C8 | D99: =IFERROR((B99-C99)/C99,"")
A100: Costi della Produzione | B100: =Input!B9 | C100: =Input!C9 | D100: =IFERROR((B100-C100)/C100,"")
A101: -Costi per Materie | B101: =Input!B10 | C101: =Input!C10 | D101: =IFERROR((B101-C101)/C101,"")
A102: % Costi Materie su Costi prod. | B102: =B$101/B$100 | C102: =C$101/C$100
A103: -Costi per Servizi | B103: =Input!B11 | C103: =Input!C11 | D103: =IFERROR((B103-C103)/C103,"")
A104: % Costi Servizi su Costi prod. | B104: =B103/B100 | C104: =C103/C100
A105: -Costi per godimento beni di terzi | B105: =Input!B12 | C105: =Input!C12 | D105: =IFERROR((B105-C105)/C105,"")
A106: % Costi Servizi su Costi prod. | B106: =B$105/B$100 | C106: =C$105/C$100
A107: -Costi Personale | B107: =Input!B13 | C107: =Input!C13 | D107: =IFERROR((B107-C107)/C107,"")
A108: % Costi Personale su Costi prod. | B108: =B107/B100 | C108: =C107/C100
A109: -Ammortamenti | B109: =Input!B14 | C109: =Input!C14 | D109: =IFERROR((B109-C109)/C109,"")
A110: % Ammortamenti su Costi prod. | B110: =B$109/B$100 | C110: =C$109/C$100
A111: -Accantonamenti per rischi | B111: =Input!B15 | C111: =Input!C15 | D111: =IFERROR((B111-C111)/C111,"")
A112: % Accantonamenti per rischi su Costi prod. | B112: =$B$111/$B$100 | C112: =$B$111/$B$100
A113: -Oneri diversi di gestione | B113: =Input!B16 | C113: =Input!C16 | D113: =IFERROR((B113-C113)/C113,"")
A114: % Oneri diversi di gestione su Costi prod. | B114: =B$113/B$100 | C114: =C$113/C$100
A115: EBIT | B115: =Input!B17 | C115: =Input!C17 | D115: =IFERROR((B115-C115)/C115,"")
A116: % EBIT su Valore Produzione | B116: =B$115/B$98 | C116: =C$115/C$98
A117: Proventi Finanziari | B117: =Input!B18 | C117: =Input!C18 | D117: =IFERROR((B117-C117)/C117,"")
A118: Oneri Finanziari | B118: =Input!B19 | C118: =Input!C19 | D118: =IFERROR((B118-C118)/C118,"")
A119: Utile (Perdita) dell'esercizio | B119: =Input!B20 | C119: =Input!C20 | D119: =IFERROR((B119-C119)/C119,"")
A120: Dipendenti | B120: =Input!B21 | C120: =Input!C21 | D120: =IFERROR((B120-C120)/C120,"")
A123: INDICI | B123: =$B$96 | C123: =$C$96
A125: Liquidità
A126: Test Acido | B126: =(B65+B69+B71)/(B83+B87) | C126: =(C65+C69+C71)/(C83+C87) | D126: =+B126-C126
A127: Current Ratio | B127: =(B63+B65+B69+B71)/(B83+B87) | C127: =(C63+C65+C69+C71)/(C83+C87) | D127: =+B127-C127
A128: Indeb. e sostenibilità del debito
A129: Rapporto Indebitamento | B129: =IF(B86=0,B82/B76,B86/B76) | C129: =IF(C86=0,C82/C76,C86/C76) | D129: =+B129-C129
A130: PFN | B130: =IF(B86=0,"Non Calcolabile",B69+B67-B86) | C130: =IF(C86=0,"Non Calcolabile",C69+C67-C86) | D130: =+B130-C130
A131: PFN/EBITDA | B131: =IF(B130="Non Calcolabile","Non Calcolabile",B130/B136) | C131: =IF(C130="Non Calcolabile","Non Calcolabile",C130/C136)
A132: Redditività
A133: ROS | B133: =B115/B99 | C133: =C115/C99 | D133: =+B133-C133
A134: ROE | B134: =B119/B76 | C134: =C119/C76 | D134: =+B134-C134
A135: ROI | B135: =B115/B73 | C135: =C115/C73 | D135: =+B135-C135
A136: EBITDA | B136: =B115+B109 | C136: =C115+C109 | D136: =+B136-C136
A137: Efficienza
A138: Asset Turnover (AT) | B138: =B99/B73 | C138: =C99/C73 | D138: =+B138-C138
A139: DSO | B139: =IF(Input!B45="n.d.","Non Calcolabile",Input!B45/Report!B98*365) | C139: =IF(Input!C45="n.d.","Non Calcolabile",Input!C45/Report!C98*365) | D139: =+B139-C139
A140: DPO | B140: =IF(Input!B44="n.d.","Non Calcolabile",Input!B44/Report!B100*365) | C140: =IF(Input!C44="n.d.","Non Calcolabile",Input!C44/Report!C100*365) | D140: =+B140-C140
A141: DIO | B141: =B63/B100*365 | C141: =C63/C100*365 | D141: =+B141-C141
A142: CCC | B142: =IF(OR(B139="Non Calcolabile",B140="Non Calcolabile"),"Non Calcolabile",B139+B141-B140) | C142: =IF(OR(C139="Non Calcolabile",C140="Non Calcolabile"),"Non Calcolabile",C139+C141-C140) | D142: =+B142-C142
